[
  {
    "name": "theme_info",
    "theme_name": "Growthx Media",
    "theme_version": "1.0.1",
    "theme_author": "Growthx Media",
    "theme_documentation_url": "https://growthxmedia.co/",
    "theme_support_url": "https://growthxmedia.co/"
  },
  {
    "name": "Extra Settings",
    "settings": [
      {
        "type": "color",
        "id": "sale_price",
        "label": "Sale Price Color",
        "default": "#d50000"
      },
      {
        "type": "color",
        "id": "theme_color",
        "label": "Theme accent",
        "info": "Show on system status bar on mobile"
      }
    ]
  },
  {
    "name": "Extended Mega Menu",
    "settings": [
      {
        "type": "select",
        "label": "Show Images on Mega Menu Links",
        "id": "extended-megamenu-show-imgs",
        "default": "no",
        "options": [
          {
            "label": "Yes",
            "value": "yes"
          },
          {
            "label": "No",
            "value": "no"
          }
        ]
      },
      {
        "type": "image_picker",
        "id": "extended-megamenu-featured-img",
        "label": "Featured Image"
      },
      {
        "type": "url",
        "id": "extended-megamenu-url",
        "label": "Featured Image URL"
      },
      {
        "type": "image_picker",
        "id": "extended-megamenu-featured-img-2",
        "label": "Featured Image"
      },
      {
        "type": "url",
        "id": "extended-megamenu-url-2",
        "label": "Featured Image URL"
      }
    ]
  },
  {
    "name": "Color\/Image swatches",
    "settings": [
      {
        "type": "text",
        "id": "optionName",
        "label": "Swatch option name",
        "default": "Color",
        "info": "Exact match is required, including capitalization."
      },
      {
        "type": "paragraph",
        "content": "If you have a multilingual store, please enter multiple options separated with commas. Example: Color,Colour,Fabre,Couleur"
      },
      {
        "type": "select",
        "id": "swatchType",
        "label": "Swatch type",
        "options": [
          {
            "value": "color",
            "label": "Color"
          },
          {
            "value": "variantImage",
            "label": "Variant image"
          }
        ],
        "default": "color"
      },
      {
        "type": "textarea",
        "id": "swatchColors",
        "label": "Colors",
        "placeholder": "Red:#ff0000\nGreen:#00ff00\nBlue:#0000ff",
        "default": "Black:#000000\nWhite:#f5f5f5\nBlue:#005eff\nRed:#c9002c\nPink:#ffd5e6\nBrown:#a2896b\nOlive:#808000\nPurple:#dac6ef\nGrey:#e2e2e7\nBeige:#d8c7af",
        "info": "One rule per line. Example: Blue:#005eff"
      },
      {
        "type": "paragraph",
        "content": "You have the option to add 2 or 3 colors for a single swatch. Example: Red&Blue: #c9002c#005eff"
      },
      {
        "type": "paragraph",
        "content": "You can also add [image files](\/admin\/content\/files?selectedView=all&media_type=Image) instead of using colors, in lowercase with spaces replaced by hyphens. Example: Green kaki: green-kaki.png"
      },
      {
        "type": "select",
        "id": "swatchStyle",
        "label": "Swatch style",
        "options": [
          {
            "value": "round",
            "label": "Round"
          },
          {
            "value": "square",
            "label": "Square"
          },
          {
            "value": "square-round-corners",
            "label": "Square round corners"
          },
          {
            "value": "portrait",
            "label": "Portrait"
          }
        ],
        "default": "round",
        "info": "Portrait mode is only available for the variant image type."
      },
      {
        "type": "range",
        "id": "swatchSize",
        "min": 20,
        "max": 120,
        "step": 2,
        "unit": "px",
        "label": "Swatch size",
        "default": 30
      },
      {
        "type": "range",
        "id": "swatchHeight",
        "min": 20,
        "max": 120,
        "step": 2,
        "unit": "px",
        "label": "Swatch Height",
        "default": 30,
        "info": "Work on portrait swatches."
      },
      {
        "type": "checkbox",
        "id": "dark",
        "label": "For dark backgrounds",
        "default": false,
        "info": "Alternate appearance for dark backgrounds."
      }
    ]
  },
  {
    "name": "Sticky Add To Cart",
    "settings": [
      {
        "type": "header",
        "content": "Sticky Add To Cart"
      },
      {
        "type": "checkbox",
        "id": "show_sticky_cart_button",
        "label": "Enable \"Sticky ATC\"",
        "info": "Quickly enable or disable this feature",
        "default": true
      },
      {
        "type": "color_scheme",
        "id": "color_scheme_main",
        "label": "t:sections.all.colors.label",
        "default": "background-1"
      },
      {
        "type": "select",
        "id": "sticky_position",
        "options": [
          {
            "value": "top",
            "label": "Top"
          },
          {
            "value": "bottom",
            "label": "Bottom"
          }
        ],
        "default": "bottom",
        "label": "Position on desktop"
      },
      {
        "type": "select",
        "id": "sticky_position_mb",
        "options": [
          {
            "value": "top",
            "label": "Top"
          },
          {
            "value": "bottom",
            "label": "Bottom"
          }
        ],
        "default": "bottom",
        "label": "Position on Mobile"
      },
      {
        "type": "select",
        "id": "title_size",
        "label": "Title Size",
        "default": "h4",
        "options": [
          {
            "value": "h1",
            "label": "H1"
          },
          {
            "value": "h2",
            "label": "H2"
          },
          {
            "value": "h3",
            "label": "H3"
          },
          {
            "value": "h4",
            "label": "H4"
          },
          {
            "value": "h5",
            "label": "H5"
          },
          {
            "value": "h6",
            "label": "H6"
          }
        ]
      },
      {
        "type": "checkbox",
        "id": "show_border",
        "default": false,
        "label": "Show Border"
      },
      {
        "type": "checkbox",
        "id": "show_title_mb",
        "default": false,
        "label": "Show Title on mobile"
      },
      {
        "type": "checkbox",
        "id": "show_price_mb",
        "default": false,
        "label": "Show Price on mobile"
      },
      {
        "type": "checkbox",
        "id": "show_price_under",
        "default": false,
        "label": "Show price under title on desktop"
      },
      {
        "type": "checkbox",
        "id": "show_img_dt",
        "default": true,
        "label": "Show image on desktop"
      },
      {
        "type": "checkbox",
        "id": "show_img_mb",
        "default": false,
        "label": "Show image on mobile"
      },
      {
        "type": "text",
        "id": "img_width",
        "default": "80",
        "label": "Image width (px)"
      },
      {
        "type": "text",
        "id": "img_height",
        "default": "80",
        "label": "Image height (px)"
      },
      {
        "type": "checkbox",
        "id": "show_quantity_input",
        "default": true,
        "label": "Show quantity field",
        "info": "On mobile devices only show when product has single variant."
      },
      {
        "type": "select",
        "id": "btn_style",
        "options": [
          {
            "value": "primary",
            "label": "Primary"
          },
          {
            "value": "secondary",
            "label": "Secondary"
          }
        ],
        "default": "primary",
        "label": "'Add to cart' button style"
      },
      {
        "type": "header",
        "content": "Advanced"
      },
      {
        "type": "range",
        "id": "offset",
        "label": "Offset",
        "min": 0,
        "max": 500,
        "step": 10,
        "default": 0,
        "info": "Adjust the offset value when showing the Sticky ATC section related to the main product form."
      },
      {
        "type": "header",
        "content": "Spacing",
        "info": "Based on 'px' values [Learn more](https:\/\/developer.mozilla.org\/en-US\/docs\/Learn\/CSS\/Building_blocks\/Values_and_units)"
      },
      {
        "type": "range",
        "id": "padding_top",
        "min": 0,
        "max": 20,
        "step": 1,
        "unit": "px",
        "label": "Padding Top",
        "default": 10
      },
      {
        "type": "range",
        "id": "padding_bottom",
        "min": 0,
        "max": 20,
        "step": 1,
        "unit": "px",
        "label": "Padding Top",
        "default": 10
      }
    ]
  },
  {
    "name": "t:settings_schema.logo.name",
    "settings": [
      {
        "type": "image_picker",
        "id": "logo",
        "label": "t:settings_schema.logo.settings.logo_image.label"
      },
      {
        "type": "range",
        "id": "logo_width",
        "min": 50,
        "max": 300,
        "step": 5,
        "default": 100,
        "unit": "px",
        "label": "t:settings_schema.logo.settings.logo_width.label"
      },
      {
        "type": "image_picker",
        "id": "second_logo",
        "label": "Second Logo"
      },
      {
        "type": "url",
        "id": "second_logo_url",
        "label": "Second Logo URL",
        "default": "/"
      },
      {
        "type": "range",
        "id": "logo_widths",
        "min": 50,
        "max": 300,
        "step": 5,
        "default": 100,
        "unit": "px",
        "label": "Second Logo Width Exhaust"
      },
      {
        "type": "image_picker",
        "id": "logo_light",
        "label": "Logo Light",
        "info": "Use for transparent header"
      },
      {
        "type": "image_picker",
        "id": "favicon",
        "label": "t:settings_schema.logo.settings.favicon.label",
        "info": "t:settings_schema.logo.settings.favicon.info"
      }
    ]
  },
  {
    "name": "t:settings_schema.colors.name",
    "settings": [
      {
        "type": "color_scheme_group",
        "id": "color_schemes",
        "definition": [
          {
            "type": "color",
            "id": "background",
            "label": "t:settings_schema.colors.settings.background.label",
            "default": "#FFFFFF"
          },
          {
            "type": "color_background",
            "id": "background_gradient",
            "label": "t:settings_schema.colors.settings.background_gradient.label",
            "info": "t:settings_schema.colors.settings.background_gradient.info"
          },
          {
            "type": "color",
            "id": "text",
            "label": "t:settings_schema.colors.settings.text.label",
            "default": "#121212"
          },
          {
            "type": "color",
            "id": "button",
            "label": "t:settings_schema.colors.settings.button_background.label",
            "default": "#121212"
          },
          {
            "type": "color",
            "id": "button_label",
            "label": "t:settings_schema.colors.settings.button_label.label",
            "default": "#FFFFFF"
          },
          {
            "type": "color",
            "id": "secondary_button_label",
            "label": "t:settings_schema.colors.settings.secondary_button_label.label",
            "default": "#121212"
          },
          {
            "type": "color",
            "id": "shadow",
            "label": "t:settings_schema.colors.settings.shadow.label",
            "default": "#121212"
          }
        ],
        "role": {
          "text": "text",
          "background": {
            "solid": "background",
            "gradient": "background_gradient"
          },
          "links": "secondary_button_label",
          "icons": "text",
          "primary_button": "button",
          "on_primary_button": "button_label",
          "primary_button_border": "button",
          "secondary_button": "background",
          "on_secondary_button": "secondary_button_label",
          "secondary_button_border": "secondary_button_label"
        }
      }
    ]
  },
  {
    "name": "t:settings_schema.typography.name",
    "settings": [
      {
        "type": "header",
        "content": "t:settings_schema.typography.settings.header__1.content"
      },
      {
        "type": "font_picker",
        "id": "type_header_font",
        "default": "assistant_n4",
        "label": "t:settings_schema.typography.settings.type_header_font.label",
        "info": "t:settings_schema.typography.settings.type_header_font.info"
      },
      {
        "type": "font_picker",
        "id": "type_header_italic_font",
        "default": "assistant_n4",
        "label": "Heading Italic Font",
        "info": "t:settings_schema.typography.settings.type_header_font.info"
      },
      {
        "type": "checkbox",
        "id": "customFont",
        "label": "Check to enable customFont",
        "default": true
      },
      {
        "type": "range",
        "id": "heading_spacing",
        "min": -1,
        "max": 3,
        "step": 0.1,
        "unit": "px",
        "label": "Letter Spacing",
        "default": 0
      },
      {
        "type": "range",
        "id": "heading_line_height",
        "min": 0.1,
        "max": 3,
        "step": 0.1,
        "label": "Line Height",
        "default": 1.4
      },
      {
        "type": "range",
        "id": "heading_scale",
        "min": 80,
        "max": 150,
        "step": 5,
        "unit": "%",
        "label": "t:settings_schema.typography.settings.heading_scale.label",
        "default": 100
      },
      {
        "type": "header",
        "content": "t:settings_schema.typography.settings.header__2.content"
      },
      {
        "type": "font_picker",
        "id": "type_body_font",
        "default": "assistant_n4",
        "label": "t:settings_schema.typography.settings.type_body_font.label",
        "info": "t:settings_schema.typography.settings.type_body_font.info"
      },
      {
        "type": "range",
        "id": "body_read",
        "min": 0,
        "max": 0.9,
        "step": 0.1,
        "unit": "px",
        "label": "Font Readabilty",
        "default": 0.5
      },
      {
        "type": "range",
        "id": "body_spacing",
        "min": -1,
        "max": 3,
        "step": 0.1,
        "unit": "px",
        "label": "Letter Spacing",
        "default": 0.5
      },
      {
        "type": "range",
        "id": "body_line_height",
        "min": -1,
        "max": 3,
        "step": 0.1,
        "label": "Line Height",
        "default": 1.4
      },
      {
        "type": "range",
        "id": "body_scale",
        "min": 70,
        "max": 130,
        "step": 5,
        "unit": "%",
        "label": "t:settings_schema.typography.settings.body_scale.label",
        "default": 100
      },
      {
        "type": "header",
        "content": "Header Menu Fonts"
      },
      {
        "type": "font_picker",
        "id": "type_menu_font",
        "default": "assistant_n4",
        "label": "Header Menu Fonts",
        "info": "t:settings_schema.typography.settings.type_body_font.info"
      },
      {
        "type": "range",
        "id": "header_menu_size",
        "min": 8,
        "max": 24,
        "step": 1,
        "unit": "px",
        "label": "Menu Size",
        "default": 14
      },
      {
        "type": "range",
        "id": "header_spacing",
        "min": -1,
        "max": 3,
        "step": 0.5,
        "unit": "px",
        "label": "Letter Spacing",
        "default": 0
      },
      {
        "type": "select",
        "id": "header_menu_transform",
        "options": [
          {
            "value": "none",
            "label": "None"
          },
          {
            "value": "uppercase",
            "label": "Uppercase"
          },
          {
            "value": "lowercase",
            "label": "Lowercase"
          }
        ],
        "default": "none",
        "label": "Text transform"
      },
      {
        "type": "header",
        "content": "Collapsible Headings"
      },
      {
        "type": "font_picker",
        "id": "type_collapsible_font",
        "default": "assistant_n4",
        "label": "Collapsible Headings Fonts",
        "info": "t:settings_schema.typography.settings.type_body_font.info"
      },
      {
        "type": "range",
        "id": "collapsible_size",
        "min": 0,
        "max": 30,
        "step": 1,
        "unit": "px",
        "label": "Collapsible Headings Size",
        "default": 16
      },
      {
        "type": "range",
        "id": "collapsible_spacing",
        "min": -1,
        "max": 3,
        "step": 0.1,
        "unit": "px",
        "label": "Collapsible Headings Spacing",
        "default": 0
      }
    ]
  },
  {
    "name": "t:settings_schema.layout.name",
    "settings": [
      {
        "type": "range",
        "id": "page_width",
        "min": 1000,
        "max": 1600,
        "step": 100,
        "default": 1200,
        "unit": "px",
        "label": "t:settings_schema.layout.settings.page_width.label"
      },
      {
        "type": "range",
        "id": "spacing_sections",
        "min": 0,
        "max": 100,
        "step": 4,
        "unit": "px",
        "label": "t:settings_schema.layout.settings.spacing_sections.label",
        "default": 0
      },
      {
        "type": "header",
        "content": "t:settings_schema.layout.settings.header__grid.content"
      },
      {
        "type": "paragraph",
        "content": "t:settings_schema.layout.settings.paragraph__grid.content"
      },
      {
        "type": "range",
        "id": "spacing_grid_horizontal",
        "min": 4,
        "max": 40,
        "step": 4,
        "default": 8,
        "unit": "px",
        "label": "t:settings_schema.layout.settings.spacing_grid_horizontal.label"
      },
      {
        "type": "range",
        "id": "spacing_grid_vertical",
        "min": 4,
        "max": 40,
        "step": 4,
        "default": 8,
        "unit": "px",
        "label": "t:settings_schema.layout.settings.spacing_grid_vertical.label"
      }
    ]
  },
  {
    "name": "t:settings_schema.animations.name",
    "settings": [
      {
        "type": "checkbox",
        "id": "animations_reveal_on_scroll",
        "label": "t:settings_schema.animations.settings.animations_reveal_on_scroll.label",
        "default": true
      },
      {
        "type": "select",
        "id": "animations_hover_elements",
        "options": [
          {
            "value": "default",
            "label": "t:settings_schema.animations.settings.animations_hover_elements.options__1.label"
          },
          {
            "value": "vertical-lift",
            "label": "t:settings_schema.animations.settings.animations_hover_elements.options__2.label"
          },
          {
            "value": "3d-lift",
            "label": "t:settings_schema.animations.settings.animations_hover_elements.options__3.label"
          }
        ],
        "default": "default",
        "label": "t:settings_schema.animations.settings.animations_hover_elements.label",
        "info": "t:settings_schema.animations.settings.animations_hover_elements.info"
      }
    ]
  },
  {
    "name": "t:settings_schema.buttons.name",
    "settings": [
      {
        "type": "header",
        "content": "t:settings_schema.global.settings.header__border.content"
      },
      {
        "type": "range",
        "id": "button_height",
        "min": 3.5,
        "max": 7,
        "step": 0.1,
        "default": 4.5,
        "unit": "rem",
        "label": "Button and Input Height"
      },
      {
        "type": "header",
        "content": "Button Fonts"
      },
      {
        "type": "font_picker",
        "id": "type_button_font",
        "default": "assistant_n4",
        "label": "Button Fonts",
        "info": "t:settings_schema.typography.settings.type_body_font.info"
      },
      {
        "type": "select",
        "id": "btn_transformation",
        "options": [
          {
            "value": "uppercase",
            "label": "Uppercase"
          },
          {
            "value": "none",
            "label": "None"
          }
        ],
        "default": "none",
        "label": "Text Style"
      },
      {
        "type": "range",
        "id": "btn_text_size",
        "min": 10,
        "max": 40,
        "step": 2,
        "unit": "px",
        "label": "Button Font Size",
        "default": 16
      },
      {
        "type": "range",
        "id": "btn_text_spacing",
        "min": -1,
        "max": 3,
        "step": 0.5,
        "unit": "px",
        "label": "Button Font Spacing",
        "default": 0
      },
      {
        "type": "range",
        "id": "buttons_border_thickness",
        "min": 0,
        "max": 12,
        "step": 1,
        "unit": "px",
        "label": "t:settings_schema.global.settings.thickness.label",
        "default": 1
      },
      {
        "type": "range",
        "id": "buttons_border_opacity",
        "min": 0,
        "max": 100,
        "step": 5,
        "unit": "%",
        "label": "t:settings_schema.global.settings.opacity.label",
        "default": 100
      },
      {
        "type": "range",
        "id": "buttons_radius",
        "min": 0,
        "max": 40,
        "step": 2,
        "unit": "px",
        "label": "t:settings_schema.global.settings.corner_radius.label",
        "default": 0
      },
      {
        "type": "header",
        "content": "t:settings_schema.global.settings.header__shadow.content"
      },
      {
        "type": "range",
        "id": "buttons_shadow_opacity",
        "min": 0,
        "max": 100,
        "step": 5,
        "unit": "%",
        "label": "t:settings_schema.global.settings.opacity.label",
        "default": 0
      },
      {
        "type": "range",
        "id": "buttons_shadow_horizontal_offset",
        "min": -12,
        "max": 12,
        "step": 2,
        "unit": "px",
        "label": "t:settings_schema.global.settings.horizontal_offset.label",
        "default": 0
      },
      {
        "type": "range",
        "id": "buttons_shadow_vertical_offset",
        "min": -12,
        "max": 12,
        "step": 2,
        "unit": "px",
        "label": "t:settings_schema.global.settings.vertical_offset.label",
        "default": 0
      },
      {
        "type": "range",
        "id": "buttons_shadow_blur",
        "min": 0,
        "max": 20,
        "step": 5,
        "unit": "px",
        "label": "t:settings_schema.global.settings.blur.label",
        "default": 0
      }
    ]
  },
  {
    "name": "t:settings_schema.variant_pills.name",
    "settings": [
      {
        "type": "paragraph",
        "content": "t:settings_schema.variant_pills.paragraph"
      },
      {
        "type": "header",
        "content": "t:settings_schema.global.settings.header__border.content"
      },
      {
        "type": "range",
        "id": "variant_pills_border_thickness",
        "min": 0,
        "max": 12,
        "step": 1,
        "unit": "px",
        "label": "t:settings_schema.global.settings.thickness.label",
        "default": 1
      },
      {
        "type": "range",
        "id": "variant_pills_border_opacity",
        "min": 0,
        "max": 100,
        "step": 5,
        "unit": "%",
        "label": "t:settings_schema.global.settings.opacity.label",
        "default": 55
      },
      {
        "type": "range",
        "id": "variant_pills_radius",
        "min": 0,
        "max": 40,
        "step": 2,
        "unit": "px",
        "label": "t:settings_schema.global.settings.corner_radius.label",
        "default": 40
      },
      {
        "type": "header",
        "content": "t:settings_schema.global.settings.header__shadow.content"
      },
      {
        "type": "range",
        "id": "variant_pills_shadow_opacity",
        "min": 0,
        "max": 100,
        "step": 5,
        "unit": "%",
        "label": "t:settings_schema.global.settings.opacity.label",
        "default": 0
      },
      {
        "type": "range",
        "id": "variant_pills_shadow_horizontal_offset",
        "min": -12,
        "max": 12,
        "step": 2,
        "unit": "px",
        "label": "t:settings_schema.global.settings.horizontal_offset.label",
        "default": 0
      },
      {
        "type": "range",
        "id": "variant_pills_shadow_vertical_offset",
        "min": -12,
        "max": 12,
        "step": 2,
        "unit": "px",
        "label": "t:settings_schema.global.settings.vertical_offset.label",
        "default": 0
      },
      {
        "type": "range",
        "id": "variant_pills_shadow_blur",
        "min": 0,
        "max": 20,
        "step": 5,
        "unit": "px",
        "label": "t:settings_schema.global.settings.blur.label",
        "default": 0
      }
    ]
  },
  {
    "name": "t:settings_schema.inputs.name",
    "settings": [
      {
        "type": "header",
        "content": "t:settings_schema.global.settings.header__border.content"
      },
      {
        "type": "range",
        "id": "inputs_border_thickness",
        "min": 0,
        "max": 12,
        "step": 1,
        "unit": "px",
        "label": "t:settings_schema.global.settings.thickness.label",
        "default": 1
      },
      {
        "type": "range",
        "id": "inputs_border_opacity",
        "min": 0,
        "max": 100,
        "step": 5,
        "unit": "%",
        "label": "t:settings_schema.global.settings.opacity.label",
        "default": 55
      },
      {
        "type": "range",
        "id": "inputs_radius",
        "min": 0,
        "max": 40,
        "step": 2,
        "unit": "px",
        "label": "t:settings_schema.global.settings.corner_radius.label",
        "default": 0
      },
      {
        "type": "header",
        "content": "t:settings_schema.global.settings.header__shadow.content"
      },
      {
        "type": "range",
        "id": "inputs_shadow_opacity",
        "min": 0,
        "max": 100,
        "step": 5,
        "unit": "%",
        "label": "t:settings_schema.global.settings.opacity.label",
        "default": 0
      },
      {
        "type": "range",
        "id": "inputs_shadow_horizontal_offset",
        "min": -12,
        "max": 12,
        "step": 2,
        "unit": "px",
        "label": "t:settings_schema.global.settings.horizontal_offset.label",
        "default": 0
      },
      {
        "type": "range",
        "id": "inputs_shadow_vertical_offset",
        "min": -12,
        "max": 12,
        "step": 2,
        "unit": "px",
        "label": "t:settings_schema.global.settings.vertical_offset.label",
        "default": 0
      },
      {
        "type": "range",
        "id": "inputs_shadow_blur",
        "min": 0,
        "max": 20,
        "step": 5,
        "unit": "px",
        "label": "t:settings_schema.global.settings.blur.label",
        "default": 0
      }
    ]
  },
  {
    "name": "t:settings_schema.cards.name",
    "settings": [
      {
        "type": "select",
        "id": "card_style",
        "options": [
          {
            "value": "standard",
            "label": "t:settings_schema.cards.settings.style.options__1.label"
          },
          {
            "value": "card",
            "label": "t:settings_schema.cards.settings.style.options__2.label"
          }
        ],
        "default": "standard",
        "label": "t:settings_schema.cards.settings.style.label"
      },
      {
        "type": "range",
        "id": "card_image_padding",
        "min": 0,
        "max": 20,
        "step": 2,
        "unit": "px",
        "label": "t:settings_schema.global.settings.image_padding.label",
        "default": 0
      },
      {
        "type": "range",
        "id": "card_title_size",
        "min": 8,
        "max": 40,
        "step": 1,
        "unit": "px",
        "label": "Title size",
        "default": 18
      },
      {
        "type": "range",
        "id": "card_price_size",
        "min": 8,
        "max": 40,
        "step": 1,
        "unit": "px",
        "label": "Price size",
        "default": 18
      },
      {
        "type": "checkbox",
        "id": "bold_font",
        "default": true,
        "label": "Bold fonts"
      },
      {
        "type": "checkbox",
        "id": "fill_space",
        "default": true,
        "label": "Fill available space",
        "info": "It will make card information to equal in height"
      },
      {
        "type": "select",
        "id": "card_text_alignment",
        "options": [
          {
            "value": "left",
            "label": "t:settings_schema.global.settings.text_alignment.options__1.label"
          },
          {
            "value": "center",
            "label": "t:settings_schema.global.settings.text_alignment.options__2.label"
          },
          {
            "value": "right",
            "label": "t:settings_schema.global.settings.text_alignment.options__3.label"
          }
        ],
        "default": "left",
        "label": "t:settings_schema.global.settings.text_alignment.label"
      },
      {
        "type": "color_scheme",
        "id": "card_color_scheme",
        "label": "t:sections.all.colors.label",
        "default": "background-2"
      },
      {
        "type": "header",
        "content": "Color Swatches"
      },
      {
        "type": "checkbox",
        "id": "swatch_show",
        "default": true,
        "label": "Show color swatches"
      },
      {
        "type": "select",
        "id": "swatch_position",
        "label": "Swatch Position",
        "options": [
          {
            "value": "top",
            "label": "On media"
          },
          {
            "value": "bottom",
            "label": "Above Title"
          }
        ],
        "default": "top",
        "info": "Color swatches position"
      },
      {
        "type": "select",
        "id": "swatchStyleCard",
        "label": "Swatch style",
        "options": [
          {
            "value": "round",
            "label": "Round"
          },
          {
            "value": "square",
            "label": "Square"
          },
          {
            "value": "square-round-corners",
            "label": "Square round corners"
          },
          {
            "value": "portrait",
            "label": "Portrait"
          }
        ],
        "default": "round",
        "info": "Portrait mode is only available for the variant image type."
      },
      {
        "type": "range",
        "id": "swatchSizeCard",
        "min": 10,
        "max": 50,
        "step": 1,
        "unit": "px",
        "label": "Swatch size",
        "default": 20
      },
      {
        "type": "header",
        "content": "Scrolling tags"
      },
      {
        "type": "checkbox",
        "id": "tag_show",
        "default": false,
        "label": "Show scrolling product tags"
      },
      {
        "type": "range",
        "id": "tag_speed",
        "min": 0,
        "max": 60,
        "step": 1,
        "unit": "sec",
        "label": "Tags Speed",
        "default": 20
      },
      {
        "type": "color_scheme",
        "id": "tag_color_scheme",
        "label": "t:sections.all.colors.label",
        "default": "background-1"
      },
      {
        "type": "range",
        "id": "card_tag_font",
        "min": 8,
        "max": 24,
        "step": 2,
        "unit": "px",
        "label": "Tag Font Size",
        "default": 14
      },
      {
        "type": "select",
        "id": "tag_transformation",
        "options": [
          {
            "value": "uppercase",
            "label": "Uppercase"
          },
          {
            "value": "none",
            "label": "None"
          }
        ],
        "default": "none",
        "label": "Text Style"
      },
      {
        "type": "select",
        "id": "tag_weight",
        "options": [
          {
            "value": "normal",
            "label": "Normal"
          },
          {
            "value": "bold",
            "label": "Bold"
          }
        ],
        "default": "normal",
        "label": "Font Style"
      },
      {
        "type": "range",
        "id": "tag_text_spacing",
        "min": -1,
        "max": 3,
        "step": 0.5,
        "unit": "px",
        "label": "Tags Font Spacing",
        "default": 0
      },
      {
        "type": "header",
        "content": "t:settings_schema.global.settings.header__border.content"
      },
      {
        "type": "range",
        "id": "card_border_thickness",
        "min": 0,
        "max": 24,
        "step": 1,
        "unit": "px",
        "label": "t:settings_schema.global.settings.thickness.label",
        "default": 0
      },
      {
        "type": "range",
        "id": "card_border_opacity",
        "min": 0,
        "max": 100,
        "step": 5,
        "unit": "%",
        "label": "t:settings_schema.global.settings.opacity.label",
        "default": 0
      },
      {
        "type": "range",
        "id": "card_corner_radius",
        "min": 0,
        "max": 40,
        "step": 2,
        "unit": "px",
        "label": "t:settings_schema.global.settings.corner_radius.label",
        "default": 0
      },
      {
        "type": "header",
        "content": "t:settings_schema.global.settings.header__shadow.content"
      },
      {
        "type": "range",
        "id": "card_shadow_opacity",
        "min": 0,
        "max": 100,
        "step": 5,
        "unit": "%",
        "label": "t:settings_schema.global.settings.opacity.label",
        "default": 10
      },
      {
        "type": "range",
        "id": "card_shadow_horizontal_offset",
        "min": -40,
        "max": 40,
        "step": 2,
        "unit": "px",
        "label": "t:settings_schema.global.settings.horizontal_offset.label",
        "default": 0
      },
      {
        "type": "range",
        "id": "card_shadow_vertical_offset",
        "min": -40,
        "max": 40,
        "step": 2,
        "unit": "px",
        "label": "t:settings_schema.global.settings.vertical_offset.label",
        "default": 0
      },
      {
        "type": "range",
        "id": "card_shadow_blur",
        "min": 0,
        "max": 40,
        "step": 5,
        "unit": "px",
        "label": "t:settings_schema.global.settings.blur.label",
        "default": 0
      }
    ]
  },
  {
    "name": "t:settings_schema.collection_cards.name",
    "settings": [
      {
        "type": "select",
        "id": "collection_card_style",
        "options": [
          {
            "value": "standard",
            "label": "t:settings_schema.collection_cards.settings.style.options__1.label"
          },
          {
            "value": "card",
            "label": "t:settings_schema.collection_cards.settings.style.options__2.label"
          }
        ],
        "default": "standard",
        "label": "t:settings_schema.collection_cards.settings.style.label"
      },
      {
        "type": "range",
        "id": "collection_card_image_padding",
        "min": 0,
        "max": 20,
        "step": 2,
        "unit": "px",
        "label": "t:settings_schema.global.settings.image_padding.label",
        "default": 0
      },
      {
        "type": "select",
        "id": "collection_card_text_alignment",
        "options": [
          {
            "value": "left",
            "label": "t:settings_schema.global.settings.text_alignment.options__1.label"
          },
          {
            "value": "center",
            "label": "t:settings_schema.global.settings.text_alignment.options__2.label"
          },
          {
            "value": "right",
            "label": "t:settings_schema.global.settings.text_alignment.options__3.label"
          }
        ],
        "default": "left",
        "label": "t:settings_schema.global.settings.text_alignment.label"
      },
      {
        "type": "color_scheme",
        "id": "collection_card_color_scheme",
        "label": "t:sections.all.colors.label",
        "default": "background-2"
      },
      {
        "type": "header",
        "content": "t:settings_schema.global.settings.header__border.content"
      },
      {
        "type": "range",
        "id": "collection_card_border_thickness",
        "min": 0,
        "max": 24,
        "step": 1,
        "unit": "px",
        "label": "t:settings_schema.global.settings.thickness.label",
        "default": 0
      },
      {
        "type": "range",
        "id": "collection_card_border_opacity",
        "min": 0,
        "max": 100,
        "step": 5,
        "unit": "%",
        "label": "t:settings_schema.global.settings.opacity.label",
        "default": 0
      },
      {
        "type": "range",
        "id": "collection_card_corner_radius",
        "min": 0,
        "max": 40,
        "step": 2,
        "unit": "px",
        "label": "t:settings_schema.global.settings.corner_radius.label",
        "default": 0
      },
      {
        "type": "header",
        "content": "t:settings_schema.global.settings.header__shadow.content"
      },
      {
        "type": "range",
        "id": "collection_card_shadow_opacity",
        "min": 0,
        "max": 100,
        "step": 5,
        "unit": "%",
        "label": "t:settings_schema.global.settings.opacity.label",
        "default": 10
      },
      {
        "type": "range",
        "id": "collection_card_shadow_horizontal_offset",
        "min": -40,
        "max": 40,
        "step": 2,
        "unit": "px",
        "label": "t:settings_schema.global.settings.horizontal_offset.label",
        "default": 0
      },
      {
        "type": "range",
        "id": "collection_card_shadow_vertical_offset",
        "min": -40,
        "max": 40,
        "step": 2,
        "unit": "px",
        "label": "t:settings_schema.global.settings.vertical_offset.label",
        "default": 0
      },
      {
        "type": "range",
        "id": "collection_card_shadow_blur",
        "min": 0,
        "max": 40,
        "step": 5,
        "unit": "px",
        "label": "t:settings_schema.global.settings.blur.label",
        "default": 0
      }
    ]
  },
  {
    "name": "t:settings_schema.blog_cards.name",
    "settings": [
      {
        "type": "select",
        "id": "blog_card_style",
        "options": [
          {
            "value": "standard",
            "label": "t:settings_schema.blog_cards.settings.style.options__1.label"
          },
          {
            "value": "card",
            "label": "t:settings_schema.blog_cards.settings.style.options__2.label"
          }
        ],
        "default": "standard",
        "label": "t:settings_schema.blog_cards.settings.style.label"
      },
      {
        "type": "range",
        "id": "blog_card_image_padding",
        "min": 0,
        "max": 20,
        "step": 2,
        "unit": "px",
        "label": "t:settings_schema.global.settings.image_padding.label",
        "default": 0
      },
      {
        "type": "select",
        "id": "blog_card_text_alignment",
        "options": [
          {
            "value": "left",
            "label": "t:settings_schema.global.settings.text_alignment.options__1.label"
          },
          {
            "value": "center",
            "label": "t:settings_schema.global.settings.text_alignment.options__2.label"
          },
          {
            "value": "right",
            "label": "t:settings_schema.global.settings.text_alignment.options__3.label"
          }
        ],
        "default": "left",
        "label": "t:settings_schema.global.settings.text_alignment.label"
      },
      {
        "type": "color_scheme",
        "id": "blog_card_color_scheme",
        "label": "t:sections.all.colors.label",
        "default": "background-2"
      },
      {
        "type": "header",
        "content": "t:settings_schema.global.settings.header__border.content"
      },
      {
        "type": "range",
        "id": "blog_card_border_thickness",
        "min": 0,
        "max": 24,
        "step": 1,
        "unit": "px",
        "label": "t:settings_schema.global.settings.thickness.label",
        "default": 0
      },
      {
        "type": "range",
        "id": "blog_card_border_opacity",
        "min": 0,
        "max": 100,
        "step": 5,
        "unit": "%",
        "label": "t:settings_schema.global.settings.opacity.label",
        "default": 0
      },
      {
        "type": "range",
        "id": "blog_card_corner_radius",
        "min": 0,
        "max": 40,
        "step": 2,
        "unit": "px",
        "label": "t:settings_schema.global.settings.corner_radius.label",
        "default": 0
      },
      {
        "type": "header",
        "content": "t:settings_schema.global.settings.header__shadow.content"
      },
      {
        "type": "range",
        "id": "blog_card_shadow_opacity",
        "min": 0,
        "max": 100,
        "step": 5,
        "unit": "%",
        "label": "t:settings_schema.global.settings.opacity.label",
        "default": 10
      },
      {
        "type": "range",
        "id": "blog_card_shadow_horizontal_offset",
        "min": -40,
        "max": 40,
        "step": 2,
        "unit": "px",
        "label": "t:settings_schema.global.settings.horizontal_offset.label",
        "default": 0
      },
      {
        "type": "range",
        "id": "blog_card_shadow_vertical_offset",
        "min": -40,
        "max": 40,
        "step": 2,
        "unit": "px",
        "label": "t:settings_schema.global.settings.vertical_offset.label",
        "default": 0
      },
      {
        "type": "range",
        "id": "blog_card_shadow_blur",
        "min": 0,
        "max": 40,
        "step": 5,
        "unit": "px",
        "label": "t:settings_schema.global.settings.blur.label",
        "default": 0
      }
    ]
  },
  {
    "name": "t:settings_schema.content_containers.name",
    "settings": [
      {
        "type": "header",
        "content": "t:settings_schema.global.settings.header__border.content"
      },
      {
        "type": "range",
        "id": "text_boxes_border_thickness",
        "min": 0,
        "max": 24,
        "step": 1,
        "unit": "px",
        "label": "t:settings_schema.global.settings.thickness.label",
        "default": 0
      },
      {
        "type": "range",
        "id": "text_boxes_border_opacity",
        "min": 0,
        "max": 100,
        "step": 5,
        "unit": "%",
        "label": "t:settings_schema.global.settings.opacity.label",
        "default": 0
      },
      {
        "type": "range",
        "id": "text_boxes_radius",
        "min": 0,
        "max": 40,
        "step": 2,
        "unit": "px",
        "label": "t:settings_schema.global.settings.corner_radius.label",
        "default": 0
      },
      {
        "type": "header",
        "content": "t:settings_schema.global.settings.header__shadow.content"
      },
      {
        "type": "range",
        "id": "text_boxes_shadow_opacity",
        "min": 0,
        "max": 100,
        "step": 5,
        "unit": "%",
        "label": "t:settings_schema.global.settings.opacity.label",
        "default": 0
      },
      {
        "type": "range",
        "id": "text_boxes_shadow_horizontal_offset",
        "min": -40,
        "max": 40,
        "step": 2,
        "unit": "px",
        "label": "t:settings_schema.global.settings.horizontal_offset.label",
        "default": 0
      },
      {
        "type": "range",
        "id": "text_boxes_shadow_vertical_offset",
        "min": -40,
        "max": 40,
        "step": 2,
        "unit": "px",
        "label": "t:settings_schema.global.settings.vertical_offset.label",
        "default": 0
      },
      {
        "type": "range",
        "id": "text_boxes_shadow_blur",
        "min": 0,
        "max": 40,
        "step": 5,
        "unit": "px",
        "label": "t:settings_schema.global.settings.blur.label",
        "default": 0
      }
    ]
  },
  {
    "name": "t:settings_schema.media.name",
    "settings": [
      {
        "type": "header",
        "content": "t:settings_schema.global.settings.header__border.content"
      },
      {
        "type": "range",
        "id": "media_border_thickness",
        "min": 0,
        "max": 24,
        "step": 1,
        "unit": "px",
        "label": "t:settings_schema.global.settings.thickness.label",
        "default": 1
      },
      {
        "type": "range",
        "id": "media_border_opacity",
        "min": 0,
        "max": 100,
        "step": 5,
        "unit": "%",
        "label": "t:settings_schema.global.settings.opacity.label",
        "default": 5
      },
      {
        "type": "range",
        "id": "media_radius",
        "min": 0,
        "max": 40,
        "step": 2,
        "unit": "px",
        "label": "t:settings_schema.global.settings.corner_radius.label",
        "default": 0
      },
      {
        "type": "header",
        "content": "t:settings_schema.global.settings.header__shadow.content"
      },
      {
        "type": "range",
        "id": "media_shadow_opacity",
        "min": 0,
        "max": 100,
        "step": 5,
        "unit": "%",
        "label": "t:settings_schema.global.settings.opacity.label",
        "default": 0
      },
      {
        "type": "range",
        "id": "media_shadow_horizontal_offset",
        "min": -40,
        "max": 40,
        "step": 2,
        "unit": "px",
        "label": "t:settings_schema.global.settings.horizontal_offset.label",
        "default": 0
      },
      {
        "type": "range",
        "id": "media_shadow_vertical_offset",
        "min": -40,
        "max": 40,
        "step": 2,
        "unit": "px",
        "label": "t:settings_schema.global.settings.vertical_offset.label",
        "default": 0
      },
      {
        "type": "range",
        "id": "media_shadow_blur",
        "min": 0,
        "max": 40,
        "step": 5,
        "unit": "px",
        "label": "t:settings_schema.global.settings.blur.label",
        "default": 0
      }
    ]
  },
  {
    "name": "t:settings_schema.popups.name",
    "settings": [
      {
        "type": "paragraph",
        "content": "t:settings_schema.popups.paragraph"
      },
      {
        "type": "header",
        "content": "t:settings_schema.global.settings.header__border.content"
      },
      {
        "type": "range",
        "id": "popup_border_thickness",
        "min": 0,
        "max": 24,
        "step": 1,
        "unit": "px",
        "label": "t:settings_schema.global.settings.thickness.label",
        "default": 1
      },
      {
        "type": "range",
        "id": "popup_border_opacity",
        "min": 0,
        "max": 100,
        "step": 5,
        "unit": "%",
        "label": "t:settings_schema.global.settings.opacity.label",
        "default": 10
      },
      {
        "type": "range",
        "id": "popup_corner_radius",
        "min": 0,
        "max": 40,
        "step": 2,
        "unit": "px",
        "label": "t:settings_schema.global.settings.corner_radius.label",
        "default": 0
      },
      {
        "type": "header",
        "content": "t:settings_schema.global.settings.header__shadow.content"
      },
      {
        "type": "range",
        "id": "popup_shadow_opacity",
        "min": 0,
        "max": 100,
        "step": 5,
        "unit": "%",
        "label": "t:settings_schema.global.settings.opacity.label",
        "default": 0
      },
      {
        "type": "range",
        "id": "popup_shadow_horizontal_offset",
        "min": -40,
        "max": 40,
        "step": 2,
        "unit": "px",
        "label": "t:settings_schema.global.settings.horizontal_offset.label",
        "default": 0
      },
      {
        "type": "range",
        "id": "popup_shadow_vertical_offset",
        "min": -40,
        "max": 40,
        "step": 2,
        "unit": "px",
        "label": "t:settings_schema.global.settings.vertical_offset.label",
        "default": 0
      },
      {
        "type": "range",
        "id": "popup_shadow_blur",
        "min": 0,
        "max": 40,
        "step": 5,
        "unit": "px",
        "label": "t:settings_schema.global.settings.blur.label",
        "default": 0
      }
    ]
  },
  {
    "name": "t:settings_schema.drawers.name",
    "settings": [
      {
        "type": "header",
        "content": "t:settings_schema.global.settings.header__border.content"
      },
      {
        "type": "range",
        "id": "drawer_border_thickness",
        "min": 0,
        "max": 24,
        "step": 1,
        "unit": "px",
        "label": "t:settings_schema.global.settings.thickness.label",
        "default": 1
      },
      {
        "type": "range",
        "id": "drawer_border_opacity",
        "min": 0,
        "max": 100,
        "step": 5,
        "unit": "%",
        "label": "t:settings_schema.global.settings.opacity.label",
        "default": 10
      },
      {
        "type": "header",
        "content": "t:settings_schema.global.settings.header__shadow.content"
      },
      {
        "type": "range",
        "id": "drawer_shadow_opacity",
        "min": 0,
        "max": 100,
        "step": 5,
        "unit": "%",
        "label": "t:settings_schema.global.settings.opacity.label",
        "default": 0
      },
      {
        "type": "range",
        "id": "drawer_shadow_horizontal_offset",
        "min": -40,
        "max": 40,
        "step": 2,
        "unit": "px",
        "label": "t:settings_schema.global.settings.horizontal_offset.label",
        "default": 0
      },
      {
        "type": "range",
        "id": "drawer_shadow_vertical_offset",
        "min": -40,
        "max": 40,
        "step": 2,
        "unit": "px",
        "label": "t:settings_schema.global.settings.vertical_offset.label",
        "default": 0
      },
      {
        "type": "range",
        "id": "drawer_shadow_blur",
        "min": 0,
        "max": 40,
        "step": 5,
        "unit": "px",
        "label": "t:settings_schema.global.settings.blur.label",
        "default": 0
      }
    ]
  },
  {
    "name": "t:settings_schema.badges.name",
    "settings": [
      {
        "type": "select",
        "id": "badge_type",
        "options": [
          {
            "value": "amount",
            "label": "Money"
          },
          {
            "value": "percent",
            "label": "Percent"
          },
          {
            "value": "sale",
            "label": "Sale"
          }
        ],
        "default": "percent",
        "label": "Badge Type"
      },
      {
        "type": "select",
        "id": "badge_icon",
        "options": [
          {
            "value": "tag",
            "label": "Tag"
          },
          {
            "value": "splash",
            "label": "Stars"
          },
          {
            "value": "none",
            "label": "None"
          }
        ],
        "default": "splash",
        "label": "Badge Icon"
      },
      {
        "type": "inline_richtext",
        "id": "sale_message",
        "label": "Badge Text",
        "default": "Save",
        "info": "Leave blank to show default"
      },
      {
        "type": "select",
        "id": "badge_position",
        "options": [
          {
            "value": "bottom left",
            "label": "t:settings_schema.badges.settings.position.options__1.label"
          },
          {
            "value": "bottom right",
            "label": "t:settings_schema.badges.settings.position.options__2.label"
          },
          {
            "value": "top left",
            "label": "t:settings_schema.badges.settings.position.options__3.label"
          },
          {
            "value": "top right",
            "label": "t:settings_schema.badges.settings.position.options__4.label"
          },
          {
            "value": "none",
            "label": "None"
          }
        ],
        "default": "bottom left",
        "label": "t:settings_schema.badges.settings.position.label"
      },
      {
        "type": "range",
        "id": "badge_border_thickness",
        "min": 0,
        "max": 12,
        "step": 1,
        "unit": "px",
        "label": "t:settings_schema.global.settings.thickness.label",
        "default": 0
      },
      {
        "type": "color",
        "id": "badge_border_color",
        "label": "Border Color",
        "default": "transparent"
      },
      {
        "type": "range",
        "id": "badge_corner_radius",
        "min": 0,
        "max": 40,
        "step": 2,
        "unit": "px",
        "label": "t:settings_schema.global.settings.corner_radius.label",
        "default": 40
      },
      {
        "type": "color_scheme",
        "id": "sale_badge_color_scheme",
        "label": "t:settings_schema.badges.settings.sale_badge_color_scheme.label",
        "default": "accent-2"
      },
      {
        "type": "color_scheme",
        "id": "sold_out_badge_color_scheme",
        "label": "t:settings_schema.badges.settings.sold_out_badge_color_scheme.label",
        "default": "inverse"
      },
      {
        "type": "checkbox",
        "id": "mfBdgs",
        "label": "Check to show Badge",
        "default":true
      }
    ]
  },
  {
    "name": "t:settings_schema.brand_information.name",
    "settings": [
      {
        "type": "paragraph",
        "content": "t:settings_schema.brand_information.settings.paragraph.content"
      },
      {
        "type": "inline_richtext",
        "id": "brand_headline",
        "label": "t:settings_schema.brand_information.settings.brand_headline.label"
      },
      {
        "type": "richtext",
        "id": "brand_description",
        "label": "t:settings_schema.brand_information.settings.brand_description.label"
      },
      {
        "type": "image_picker",
        "id": "brand_image",
        "label": "t:settings_schema.brand_information.settings.brand_image.label"
      },
      {
        "type": "range",
        "id": "brand_image_width",
        "min": 50,
        "max": 550,
        "step": 5,
        "default": 100,
        "unit": "px",
        "label": "t:settings_schema.brand_information.settings.brand_image_width.label"
      }
    ]
  },
  {
    "name": "t:settings_schema.social-media.name",
    "settings": [
      {
        "type": "header",
        "content": "t:settings_schema.social-media.settings.header.content"
      },
      {
        "type": "text",
        "id": "social_facebook_link",
        "label": "t:settings_schema.social-media.settings.social_facebook_link.label",
        "placeholder": "t:settings_schema.social-media.settings.social_facebook_link.info"
      },
      {
        "type": "text",
        "id": "social_instagram_link",
        "label": "t:settings_schema.social-media.settings.social_instagram_link.label",
        "placeholder": "t:settings_schema.social-media.settings.social_instagram_link.info"
      },
      {
        "type": "text",
        "id": "social_youtube_link",
        "label": "t:settings_schema.social-media.settings.social_youtube_link.label",
        "placeholder": "t:settings_schema.social-media.settings.social_youtube_link.info"
      },
      {
        "type": "text",
        "id": "social_tiktok_link",
        "label": "t:settings_schema.social-media.settings.social_tiktok_link.label",
        "placeholder": "t:settings_schema.social-media.settings.social_tiktok_link.info"
      },
      {
        "type": "text",
        "id": "social_twitter_link",
        "label": "t:settings_schema.social-media.settings.social_twitter_link.label",
        "placeholder": "t:settings_schema.social-media.settings.social_twitter_link.info"
      },
      {
        "type": "text",
        "id": "social_snapchat_link",
        "label": "t:settings_schema.social-media.settings.social_snapchat_link.label",
        "placeholder": "t:settings_schema.social-media.settings.social_snapchat_link.info"
      },
      {
        "type": "text",
        "id": "social_pinterest_link",
        "label": "t:settings_schema.social-media.settings.social_pinterest_link.label",
        "placeholder": "t:settings_schema.social-media.settings.social_pinterest_link.info"
      },
      {
        "type": "text",
        "id": "social_tumblr_link",
        "label": "t:settings_schema.social-media.settings.social_tumblr_link.label",
        "placeholder": "t:settings_schema.social-media.settings.social_tumblr_link.info"
      },
      {
        "type": "text",
        "id": "social_vimeo_link",
        "label": "t:settings_schema.social-media.settings.social_vimeo_link.label",
        "placeholder": "t:settings_schema.social-media.settings.social_vimeo_link.info"
      }
    ]
  },
  {
    "name": "t:settings_schema.search_input.name",
    "settings": [
      {
        "type": "header",
        "content": "t:settings_schema.search_input.settings.header.content"
      },
      {
        "type": "checkbox",
        "id": "predictive_search_enabled",
        "default": true,
        "label": "t:settings_schema.search_input.settings.predictive_search_enabled.label"
      },
      {
        "type": "checkbox",
        "id": "predictive_search_show_vendor",
        "default": false,
        "label": "t:settings_schema.search_input.settings.predictive_search_show_vendor.label",
        "info": "t:settings_schema.search_input.settings.predictive_search_show_vendor.info"
      },
      {
        "type": "checkbox",
        "id": "predictive_search_show_price",
        "default": false,
        "label": "t:settings_schema.search_input.settings.predictive_search_show_price.label",
        "info": "t:settings_schema.search_input.settings.predictive_search_show_price.info"
      }
    ]
  },
  {
    "name": "t:settings_schema.currency_format.name",
    "settings": [
      {
        "type": "header",
        "content": "t:settings_schema.currency_format.settings.content"
      },
      {
        "type": "paragraph",
        "content": "t:settings_schema.currency_format.settings.paragraph"
      },
      {
        "type": "checkbox",
        "id": "currency_code_enabled",
        "label": "t:settings_schema.currency_format.settings.currency_code_enabled.label",
        "default": true
      },
      {
        "type": "header",
        "content": "t:settings_schema.currency_format.settings.sup_enabled.label"
      },
      {
        "type": "paragraph",
        "content": "t:settings_schema.currency_format.settings.sup_enabled.paragraph"
      },
      {
        "type": "checkbox",
        "id": "sup_enabled",
        "label": "t:settings_schema.currency_format.settings.sup_enabled.label",
        "default": false
      }
    ]
  },
  {
    "name": "t:settings_schema.cart.name",
    "settings": [
      {
        "type": "select",
        "id": "cart_type",
        "options": [
          {
            "value": "drawer",
            "label": "t:settings_schema.cart.settings.cart_type.drawer.label"
          },
          {
            "value": "page",
            "label": "t:settings_schema.cart.settings.cart_type.page.label"
          },
          {
            "value": "notification",
            "label": "t:settings_schema.cart.settings.cart_type.notification.label"
          }
        ],
        "default": "notification",
        "label": "t:settings_schema.cart.settings.cart_type.label"
      },
      {
        "type": "text",
        "id": "crtTxt",
        "label": "Enter Cart Title Text",
        "default":"Lorem Ipsum"
      },
      {
        "type": "image_picker",
        "id": "paymentImg",
        "label": "Select Payment Images"
      },
      {
        "type": "checkbox",
        "id": "show_vendor",
        "label": "t:settings_schema.cart.settings.show_vendor.label",
        "default": false
      },
      {
        "type": "checkbox",
        "id": "show_cart_note",
        "label": "t:settings_schema.cart.settings.show_cart_note.label",
        "default": false
      },
      {
        "type": "color",
        "id": "note_bg_color",
        "label": "Background Color",
        "default": "#f2f2f2"
      },
      {
        "type": "range",
        "id": "cart_note_radius",
        "min": 0,
        "max": 40,
        "step": 2,
        "unit": "px",
        "label": "t:settings_schema.global.settings.corner_radius.label",
        "default": 0
      },
      {
        "type": "header",
        "content": "t:settings_schema.cart.settings.cart_drawer.header"
      },
      {
        "type": "collection",
        "id": "cart_drawer_collection",
        "label": "t:settings_schema.cart.settings.cart_drawer.collection.label",
        "info": "t:settings_schema.cart.settings.cart_drawer.collection.info"
      },
      {
        "type": "color_scheme",
        "id": "cart_color_scheme",
        "label": "t:sections.all.colors.label",
        "default": "background-1"
      }
    ]
  },
  {
    "name": "t:settings_schema.lumin-freeshipping-bar.name",
    "settings": [
      {
        "type": "checkbox",
        "id": "fsb_enable",
        "label": "Enable\/Disable Free Shipping Bar",
        "default": true
      },
      {
        "type": "checkbox",
        "id": "fsb_ajax",
        "label": "Enable\/Disable Ajax Functionality",
        "default": true
      },
      {
        "type": "header",
        "content": "Goal"
      },
      {
        "type": "text",
        "id": "fsb_goal",
        "label": "Cart Goal",
        "default": "99",
        "info": "Ammount For Free Shipping"
      },
      {
        "type": "header",
        "content": "Headline Steps"
      },
      {
        "type": "inline_richtext",
        "id": "fsb_headline_start",
        "label": "Start Headline",
        "default": "If you add (x) worth of products to your cart, you'll get Freeshipping!",
        "info": "Use the special character '(x)' as a placeholder for the 'Goal' amount"
      },
      {
        "type": "inline_richtext",
        "id": "fsb_headline_middle",
        "label": "Middle Headline",
        "default": "You are (x) away from Freeshipping!",
        "info": "Use the special character '(x)' as a placeholder for the 'Remaining' amount"
      },
      {
        "type": "inline_richtext",
        "id": "fsb_headline_end",
        "label": "End Headline",
        "default": "You have Freeshipping!",
        "info": "Use the special character '(x)' as a placeholder for the 'Goal' amount"
      },
      {
        "type": "select",
        "id": "text_align",
        "options": [
          {
            "value": "left",
            "label": "Left"
          },
          {
            "value": "center",
            "label": "Center"
          },
          {
            "value": "right",
            "label": "Right"
          }
        ],
        "default": "center",
        "label": "Text Alignment"
      },
      {
        "type": "header",
        "content": "Colors"
      },
      {
        "type": "color_scheme",
        "id": "bar_color_scheme",
        "label": "Container Color",
        "default": "background-1"
      },
      {
        "type": "color",
        "id": "fsb_background_color",
        "label": "Bar Background Color",
        "default": "#fefeee"
      },
      {
        "type": "color",
        "id": "fsb_progress_color",
        "label": "Progress Bar Color",
        "default": "#ff3484"
      },
      {
        "type": "color",
        "id": "fsb_progress_color_2",
        "label": "Progress Bar Color 2",
        "default": "#f1e04d"
      },
      {
        "type": "color",
        "id": "fsb_text_color",
        "label": "Text Background Color",
        "default": "#FFFFFF"
      },
      {
        "type": "color",
        "id": "fsb_border_color",
        "label": "Border Color",
        "default": "#efefef"
      },
      {
        "type": "range",
        "id": "bar_height",
        "min": 1,
        "max": 20,
        "step": 1,
        "unit": "px",
        "label": "Bar Height",
        "default": 5
      },
      {
        "type": "range",
        "id": "in_bar_radius",
        "min": 0,
        "max": 100,
        "step": 1,
        "unit": "px",
        "label": "Bar Corner Radius",
        "default": 0
      },
      {
        "type": "range",
        "id": "bar_radius",
        "min": 0,
        "max": 100,
        "step": 1,
        "unit": "px",
        "label": "Container Corner Radius",
        "default": 0
      },
      {
        "type": "color",
        "id": "fsb_accent_color",
        "label": "Accent Color",
        "default": "#558018"
      }
    ]
  },
  {
    "name": "Cart Upsell",
    "settings": [
      {
        "type": "header",
        "content": "Cart Upsell",
        "info": "Visible on cart drawer only."
      },
      {
        "type": "color_scheme",
        "id": "upsell_main_color_scheme",
        "label": "t:sections.all.colors.label",
        "default": "background-1"
      },
      {
        "type": "color_scheme",
        "id": "upsell_color_scheme",
        "label": "t:sections.all.colors.label",
        "default": "background-1",
        "info": "Product Card Color"
      },
      {
        "type": "collection",
        "id": "collection",
        "label": "Collection"
      },
      {
        "type": "range",
        "id": "limit",
        "label": "Limit products",
        "min": 2,
        "max": 24,
        "default": 4
      },
      {
        "type": "text",
        "id": "title",
        "label": "Title",
        "default": "You might like..."
      },
      {
        "type": "text_alignment",
        "id": "title_text_align",
        "label": "Title text-align",
        "default": "left"
      },
      {
        "type": "select",
        "id": "list_style_cart_drawer",
        "label": "List style - cart drawer",
        "options": [
          {
            "value": "scroll",
            "label": "Scroll"
          },
          {
            "value": "stack",
            "label": "Stack"
          }
        ],
        "default": "stack"
      },
      {
        "type": "select",
        "id": "upsell_btn_style",
        "label": "Button style",
        "options": [
          {
            "value": "primary",
            "label": "Primary"
          },
          {
            "value": "secondary",
            "label": "Secondary"
          }
        ],
        "default": "primary"
      },
      {
        "type": "text",
        "id": "upsell_btn_text",
        "label": "Cart Button Text",
        "default": "+ Add",
        "info": "Leave blank to show default"
      }
    ]
  },
  {
    "name": "Cart Gift Wrap",
    "settings": [
      {
        "type": "checkbox",
        "id": "enable_cart_upsell",
        "label": "Enable Cart Upsell Checkbox",
        "default": false
      },
      {
        "type": "color",
        "id": "toggle_color",
        "label": "Toggle Button Color",
        "default": "#78b333"
      },
      {
        "type": "color",
        "id": "gift_price_color",
        "label": "Price Color",
        "default": "#212121"
      },
      {
        "type": "color",
        "id": "gift_bg_color",
        "label": "Background Color",
        "default": "#f2f2f2"
      },
      {
        "type": "range",
        "id": "gift_wrap_radius",
        "min": 0,
        "max": 40,
        "step": 2,
        "unit": "px",
        "label": "t:settings_schema.global.settings.corner_radius.label",
        "default": 0
      },
      {
        "type": "product",
        "id": "cart_upsell_product",
        "label": "Cart Upsell Product",
        "info": "Note: Defaults to first variant of the selected product"
      },
      {
        "type": "image_picker",
        "id": "gift_icon",
        "label": "Gift Image"
      },
      {
        "type": "text",
        "id": "cart_upsell_text",
        "label": "Cart Upsell Text",
        "default": "Add Gift Wrap"
      },
      {
        "type": "range",
        "id": "cart_upsell_font_size",
        "label": "Font Size",
        "min": 10,
        "max": 20,
        "default": 14
      },
      {
        "type": "select",
        "id": "cart_upsell_font_weight",
        "label": "Font Weight",
        "options": [
          {
            "value": "400",
            "label": "Normal"
          },
          {
            "value": "500",
            "label": "Semi-Bold"
          },
          {
            "value": "600",
            "label": "Bold"
          }
        ],
        "default": "400"
      },
      {
        "type": "text",
        "id": "cart_upsell_subtext",
        "label": "Cart Upsell description",
        "default": "Description here"
      },
      {
        "type": "range",
        "id": "cart_upsell_subtext_size",
        "label": "Font Size",
        "min": 10,
        "max": 20,
        "default": 13
      },
      {
        "type": "select",
        "id": "cart_upsell_sub_weight",
        "label": "Font Weight",
        "options": [
          {
            "value": "400",
            "label": "Normal"
          },
          {
            "value": "500",
            "label": "Semi-Bold"
          },
          {
            "value": "600",
            "label": "Bold"
          }
        ],
        "default": "400"
      }
    ]
  }
]
